Workbook

Sheet Loss Rasio Per Produk
A2: LOSS RATIO (LOR)
A3: COB | B3: BUSINESS CODE | C3: BUSINESS NAME | D3: 2023 | E3: 2024 | F3: 2025
A4: PROPERTY | B4: R01 | C4: FIRE (DAI) | D4: 0.0023913174 | E4: 0.81470704 | F4: 0.25460701
A5: PROPERTY | B5: R02 | C5: FIRE (PAR/CAR) | D5: 0.92720449 | E5: 1.6821218 | F5: 0.25460701
A6: PROPERTY | B6: R03 | C6: EARTHQUAKE | D6: 0 | E6: 0 | F6: 0.25460701
A7: PROPERTY | B7: R04 | C7: CONSORTIUM | D7: 0 | E7: 0 | F7: 0.25460701
A8: PROPERTY | B8: R05 | C8: FIRE (RELIHOME) | D8: 0 | E8: 0 | F8: 0.25460701
A9: PROPERTY | B9: R06 | C9: FIRE (HOUSEHOLD CONTENT) | D9: 0 | E9: 0 | F9: 0.25460701
A10: PROPERTY | B10: R07 | C10: BUSINESS INTERRUPTION | D10: 0 | E10: 0 | F10: 0.25460701
A11: MARINE CARGO | B11: C01 | C11: EXPORT | D11: 0 | E11: 0 | F11: 0.1525408
A12: MARINE CARGO | B12: C02 | C12: IMPORT | D12: 0 | E12: 0.017797526 | F12: 0.1525408
A13: MARINE CARGO | B13: C03 | C13: INTER INSULER | D13: 0.10860875 | E13: 0.35538815 | F13: 0.1525408
A14: MARINE CARGO | B14: C04 | C14: LAND TRANSIT | D14: 0.10464781 | E14: 0.096849793 | F14: 0.1525408
... A39: GENERAL ACCIDENT | B39: A18 | C39: EXTENDED WARRANTY MACHINERY OF CAR | D39: 0 | E39: 0 | F39: 0.054712509
A40: LIABILITY | B40: A19 | D40: 0 | E40: 0 | F40: 0.0318734
A41: CREDIT | B41: A20 | C41: ASURANSI KREDIT MULTIGUNA | D41: 0 | E41: 0.88546239 | F41: 0.88546239
A42: GENERAL ENGINEERING | B42: E01 | C42: CONTRACTORS ALL RISK | D42: 0 | E42: 0 | F42: 0.21827839
A43: GENERAL ENGINEERING | B43: E02 | C43: ERECTION ALL RISK | D43: 0 | E43: 0 | F43: 0.21827839
A44: GENERAL ENGINEERING | B44: E03 | C44: MACHINERY BREAKDOWN | D44: 0.32265987 | E44: 0.14233173 | F44: 0.21827839
A45: GENERAL ENGINEERING | B45: E04 | C45: BOILER EXPLOSION INSURANCE | D45: 0 | E45: 0 | F45: 0.21827839
A46: GENERAL ENGINEERING | B46: E05 | C46: ELECTRONIC EQUIPMENT INSURANCE | D46: 0 | E46: 0 | F46: 0.21827839
A47: GENERAL ENGINEERING | B47: E06 | C47: CIVIL ENGINEERING COMPLETED RISK | D47: 0 | E47: 0 | F47: 0.21827839
A48: GENERAL ENGINEERING | B48: E07 | C48: CONTRACTOR PLANT AND MACHINERY INSURANCE | D48: 0.41653608 | E48: 0.27359119 | F48: 0.21827839
A49: GENERAL ACCIDENT | B49: S01 | C49: ENGINEERING | D49: 0 | E49: 0 | F49: 0.054712509
A50: GENERAL ACCIDENT | B50: S02 | C50: THEFT | D50: 0 | E50: 0 | F50: 0.054712509
A51: GENERAL ACCIDENT | B51: S03 | C51: LIABILITY | D51: 0 | E51: 0 | F51: 0.054712509
A52: GENERAL ACCIDENT | B52: S05 | C52: AVIATION | D52: 0 | E52: 0 | F52: 0.054712509
... A64: MOTOR VEHICLE | B64: V04 | C64: MOTOR CYCLE | D64: 0.092301475 | E64: 0.36491602 | F64: 0.50675333

Sheet Loss Rasio Per COB
B2: LOSS RASIO
B3: COB | C3: 2020 | D3: 2021 | E3: 2022 | F3: 2023 | G3: 2024 | H3: 2025
B4: Property | C4: 0.51 | D4: 0.48 | E4: 0.431 | F4: 0.76229247 | G4: 1.226334 | H4: 0.25460701
B5: Marine Cargo | C5: 0.12 | D5: 0.07 | E5: 0.046 | F5: 0.22852501 | G5: 0.2508365 | H5: 0.1525408
B6: Marine Hull | C6: 0.31 | D6: 0.29 | E6: 0.046 | F6: 0.050898567 | G6: 0.11952308 | H6: 0.017122117
B7: Motor Vehicle | C7: 0.5 | D7: 0.45 | E7: 0.431 | F7: 0.52412827 | G7: 0.59947946 | H7: 0.50675333
B8: General Accident | C8: 0.68 | D8: 0.67 | E8: 0.741 | F8: 0.078311103 | G8: 0.075049447 | H8: 0.054712509
B9: General Engineering | C9: 0.75 | D9: 0.56 | E9: 0.234 | F9: 0.5291544 | G9: 0.26225301 | H9: 0.21827839
B10: Liability | C10: 0.68 | D10: 0.67 | E10: 0.741 | F10: 0.089811745 | G10: 1.0417618 | H10: 0.0318734
B11: Credit Stoploss | F11: 0.90140809 | G11: 0.88546239 | H11: 0.56927249
B12: Health | C12: 0.95 | D12: 0.84 | E12: 0.668 | F12: 1.0364014 | G12: 0.62716313 | H12: 0.40093522

Sheet PAD
B2: PAD Gross CL 75% | J2: PAD Reas CL 75% | R2: PAD Net CL 75%
B3: COB | C3: 2020 | D3: 2021 | E3: 2022 | F3: 2023 | G3: 2024 | H3: 2025 | J3: COB | K3: 2020 | L3: 2021 | M3: 2022 | N3: 2023 | O3: 2024 | P3: 2025 | R3: COB | S3: 2020 | T3: 2021 | U3: 2022 | V3: 2023 | W3: 2024 | X3: 2025
B4: Property | C4: 0.075 | D4: 0.075 | E4: 0.075 | F4: 0.075 | G4: 0.075 | H4: 0.18332768 | J4: Property | K4: 0.075 | L4: 0.075 | M4: 0.075 | N4: 0.075 | O4: 0.075 | P4: 0.1795279 | R4: Property | S4: 0.075 | T4: 0.075 | U4: 0.075 | V4: 0.075 | W4: 0.075 | X4: 0.12804715
B5: Marine Cargo | C5: 0.075 | D5: 0.075 | E5: 0.075 | F5: 0.075 | G5: 0.075 | H5: 0.18515204 | J5: Marine Cargo | K5: 0.075 | L5: 0.075 | M5: 0.075 | N5: 0.075 | O5: 0.075 | P5: 0 | R5: Marine Cargo | S5: 0.075 | T5: 0.075 | U5: 0.075 | V5: 0.075 | W5: 0.075 | X5: 0.18515204
B6: Marine Hull | C6: 0.075 | D6: 0.075 | E6: 0.075 | F6: 0.075 | G6: 0.075 | H6: 0.13292443 | J6: Marine Hull | K6: 0.075 | L6: 0.075 | M6: 0.075 | N6: 0.075 | O6: 0.075 | P6: 0.10237512 | R6: Marine Hull | S6: 0.075 | T6: 0.075 | U6: 0.075 | V6: 0.075 | W6: 0.075 | X6: 0.10370761
B7: Motor Vehicle | C7: 0.075 | D7: 0.075 | E7: 0.075 | F7: 0.075 | G7: 0.075 | H7: 0.070186259 | J7: Motor Vehicle | K7: 0.075 | L7: 0.075 | M7: 0.075 | N7: 0.075 | O7: 0.075 | P7: 0.11681974 | R7: Motor Vehicle | S7: 0.075 | T7: 0.075 | U7: 0.075 | V7: 0.075 | W7: 0.075 | X7: 0.065686103
B8: General Accident | C8: 0.075 | D8: 0.075 | E8: 0.075 | F8: 0.075 | G8: 0.075 | H8: 0.13292443 | J8: General Accident | K8: 0.075 | L8: 0.075 | M8: 0.075 | N8: 0.075 | O8: 0.075 | P8: 0.10237512 | R8: General Accident | S8: 0.075 | T8: 0.075 | U8: 0.075 | V8: 0.075 | W8: 0.075 | X8: 0.10370761
B9: General Engineering | C9: 0.075 | D9: 0.075 | E9: 0.075 | F9: 0.075 | G9: 0.075 | H9: 0.13292443 | J9: General Engineering | K9: 0.075 | L9: 0.075 | M9: 0.075 | N9: 0.075 | O9: 0.075 | P9: 0.10237512 | R9: General Engineering | S9: 0.075 | T9: 0.075 | U9: 0.075 | V9: 0.075 | W9: 0.075 | X9: 0.10370761
B10: Liability | C10: 0.075 | D10: 0.075 | E10: 0.075 | F10: 0.075 | G10: 0.075 | H10: 0.13292443 | J10: Liability | K10: 0.075 | L10: 0.075 | M10: 0.075 | N10: 0.075 | O10: 0.075 | P10: 0.10237512 | R10: Liability | S10: 0.075 | T10: 0.075 | U10: 0.075 | V10: 0.075 | W10: 0.075 | X10: 0.10370761
B11: Credit Stoploss | J11: Credit Stoploss | R11: Credit Stoploss
B12: Health | C12: 0.075 | D12: 0.075 | E12: 0.075 | F12: 0.075 | G12: 0.075 | H12: 0.15444202 | J12: Health | K12: 0.075 | L12: 0.075 | M12: 0.075 | N12: 0.075 | O12: 0.075 | P12: 0 | R12: Health | S12: 0.075 | T12: 0.075 | U12: 0.075 | V12: 0.075 | W12: 0.075 | X12: 0.15444202
B14: PAD Gross CL 95% | J14: PAD Reas CL 95% | R14: PAD Net CL 95%
B15: COB | C15: 2020 | D15: 2021 | E15: 2022 | F15: 2023 | G15: 2024 | H15: 2025 | J15: COB | K15: 2020 | L15: 2021 | M15: 2022 | N15: 2023 | O15: 2024 | P15: 2025 | R15: COB | S15: 2020 | T15: 2021 | U15: 2022 | V15: 2023 | W15: 2024 | X15: 2025
B16: Property | C16: 0.095 | D16: 0.095 | E16: 0.095 | F16: 0.095 | G16: 0.095 | H16: 0.52685888 | J16: Property | K16: 0.095 | L16: 0.095 | M16: 0.095 | N16: 0.095 | O16: 0.095 | P16: 0.51093497 | R16: Property | S16: 0.095 | T16: 0.095 | U16: 0.095 | V16: 0.095 | W16: 0.095 | X16: 0.35452325
B17: Marine Cargo | C17: 0.095 | D17: 0.095 | E17: 0.095 | F17: 0.095 | G17: 0.095 | H17: 0.56626856 | J17: Marine Cargo | K17: 0.095 | L17: 0.095 | M17: 0.095 | N17: 0.095 | O17: 0.095 | P17: 0 | R17: Marine Cargo | S17: 0.095 | T17: 0.095 | U17: 0.095 | V17: 0.095 | W17: 0.095 | X17: 0.56626856
B18: Marine Hull | C18: 0.095 | D18: 0.095 | E18: 0.095 | F18: 0.095 | G18: 0.095 | H18: 0.34894573 | J18: Marine Hull | K18: 0.095 | L18: 0.095 | M18: 0.095 | N18: 0.095 | O18: 0.095 | P18: 0.26902145 | R18: Marine Hull | S18: 0.095 | T18: 0.095 | U18: 0.095 | V18: 0.095 | W18: 0.095 | X18: 0.30929097
B19: Motor Vehicle | C19: 0.095 | D19: 0.095 | E19: 0.095 | F19: 0.095 | G19: 0.095 | H19: 0.1931733 | J19: Motor Vehicle | K19: 0.095 | L19: 0.095 | M19: 0.095 | N19: 0.095 | O19: 0.095 | P19: 0.33022113 | R19: Motor Vehicle | S19: 0.095 | T19: 0.095 | U19: 0.095 | V19: 0.095 | W19: 0.095 | X19: 0.19699391
B20: General Accident | C20: 0.095 | D20: 0.095 | E20: 0.095 | F20: 0.095 | G20: 0.095 | H20: 0.34894573 | J20: General Accident | K20: 0.095 | L20: 0.095 | M20: 0.095 | N20: 0.095 | O20: 0.095 | P20: 0.26902145 | R20: General Accident | S20: 0.095 | T20: 0.095 | U20: 0.095 | V20: 0.095 | W20: 0.095 | X20: 0.30929097
B21: General Engineering | C21: 0.095 | D21: 0.095 | E21: 0.095 | F21: 0.095 | G21: 0.095 | H21: 0.34894573 | J21: General Engineering | K21: 0.095 | L21: 0.095 | M21: 0.095 | N21: 0.095 | O21: 0.095 | P21: 0.26902145 | R21: General Engineering | S21: 0.095 | T21: 0.095 | U21: 0.095 | V21: 0.095 | W21: 0.095 | X21: 0.30929097
B22: Liability | C22: 0.095 | D22: 0.095 | E22: 0.095 | F22: 0.095 | G22: 0.095 | H22: 0.34894573 | J22: Liability | K22: 0.095 | L22: 0.095 | M22: 0.095 | N22: 0.095 | O22: 0.095 | P22: 0.26902145 | R22: Liability | S22: 0.095 | T22: 0.095 | U22: 0.095 | V22: 0.095 | W22: 0.095 | X22: 0.30929097
B23: Credit Stoploss | J23: Credit Stoploss | R23: Credit Stoploss
B24: Health | C24: 0.095 | D24: 0.095 | E24: 0.095 | F24: 0.095 | G24: 0.095 | H24: 0.42386138 | J24: Health | K24: 0.095 | L24: 0.095 | M24: 0.095 | N24: 0.095 | O24: 0.095 | P24: 0 | R24: Health | S24: 0.095 | T24: 0.095 | U24: 0.095 | V24: 0.095 | W24: 0.095 | X24: 0.42386138

Sheet ICHE
B3: ICHE
B4: COB | C4: 2020 | D4: 2021 | E4: 2022 | F4: 2023 | G4: 2024 | H4: 2025
B5: Property | C5: 0 | D5: 0 | E5: 0 | F5: 0 | G5: 0 | H5: 0.025
B6: Marine Cargo | C6: 0 | D6: 0 | E6: 0 | F6: 0 | G6: 0 | H6: 0.025
B7: Marine Hull | C7: 0 | D7: 0 | E7: 0 | F7: 0 | G7: 0 | H7: 0.025
B8: Motor Vehicle | C8: 0 | D8: 0 | E8: 0 | F8: 0 | G8: 0 | H8: 0.025
B9: General Accident | C9: 0 | D9: 0 | E9: 0 | F9: 0 | G9: 0 | H9: 0.025
B10: General Engineering | C10: 0 | D10: 0 | E10: 0 | F10: 0 | G10: 0 | H10: 0.025
B11: Liability | C11: 0 | D11: 0 | E11: 0 | F11: 0 | G11: 0 | H11: 0.025
B12: Credit | C12: 0 | D12: 0 | E12: 0 | F12: 0 | G12: 0 | H12: 0.025
B13: Health | C13: 0 | D13: 0 | E13: 0 | F13: 0 | G13: 0 | H13: 0.025

Sheet Bunga Diskonto
B1: [Indonesian Gov Bond Yield (IDR)] - 31 Des 2020 | R1: [Indonesian Gov Bond Yield (IDR)] - 31 Des 2021 | AH1: [Indonesian Gov Bond Yield Spot Rate + Illiquid (IDR)] - 31 Des 2022 | AY1: [Indonesian Gov Bond Yield (IDR)] - 31 Des 2023 | BO1: [Indonesian Gov Bond Yield (IDR)] - 31 Des 2024 | CE1: [Indonesian Gov Bond Yield Spot Rate + Illiquid (IDR)] - 31 Des 2025
B2: Term | C2: 43861 | D2: 43889 | E2: 43921 | F2: 43951 | G2: 43982 | H2: 44012 | I2: 44043 | J2: 44074 | K2: 44104 | L2: 44135 | M2: 44165 | N2: 44196 | O2: SAK | P2: SAP | R2: Term | S2: 44227 | T2: 2/29/2021 | U2: 44286 | V2: 44316 | W2: 44347 | X2: 44377 | Y2: 44408 | Z2: 44439 | AA2: 44469 | AB2: 44500 | AC2: 44530 | AD2: 44561 | AE2: SAK | AF2: SAP | AH2: Term | AI2: 44592 | AJ2: 44620 | AK2: 44651 | AL2: 44681 | AM2: 44712 | AN2: 44742 | AO2: 44773 | AP2: 44804 | AQ2: 44834 | AR2: 44865 | AS2: 44895 | AT2: 44926 | AU2: SAK | AV2: SAP | AY2: Term | AZ2: 44957 | BA2: 44985 | BB2: 45016 | BC2: 45046 | BD2: 45077 | BE2: 45107 | BF2: 45138 | BG2: 45169 | BH2: 45199 | BI2: 45230 | BJ2: 45260 | BK2: 45291 | BL2: SAK | BM2: SAP | BO2: Term | BP2: 45322 | BQ2: 45351 | BR2: 45382 | BS2: 45412 | BT2: 45443 | BU2: 45473 | BV2: 45504 | BW2: 45535 | BX2: 45565 | BY2: 45596 | BZ2: 45626 | CA2: 45657 | CB2: SAK | CC2: SAP | CE2: Term | CF2: 45688 | CG2: 45716 | CH2: 45747 | CI2: 45777 | CJ2: 45808 | CK2: 45838 | CL2: 45869 | CM2: 45900 | CN2: 45930 | CO2: 45961 | CP2: 45991 | CQ2: 46022 | CR2: SAK | CS2: SAP
B3: 0 | C3: 4.2625 | D3: 4.1235 | E3: 3.8851 | F3: 4.3103 | G3: 3.5541 | H3: 3.4822 | I3: 3.3836 | J3: 3.09445 | K3: 2.8053 | L3: 2.6771 | M3: 1.8493 | N3: 2.9413 | O3: =N3/100 -> 0.029413 | P3: =AVERAGE(C3:N3)/100 -> 0.033640625 | R3: 0 | S3: 3.1578 | T3: 3.3691 | U3: 3.2485 | V3: 3.1409 | W3: 3.0513 | X3: 2.7974 | Y3: 2.2274 | Z3: 2.1057 | AA3: 2.368 | AB3: 2.8398 | AC3: 2.9847 | AD3: 2.8303 | AE3: =AD3/100 -> 0.028303 | AF3: =AVERAGE(S3:AD3)/100 -> 0.028434083 | AH3: 0 | AI3: 2.676047 | AJ3: 2.1812 | AK3: 2.3639 | AL3: 2.457325 | AM3: 3.2487 | AN3: 3.3271 | AO3: 2.1076 | AP3: 1.796 | AQ3: 3.7804 | AR3: 3.6952 | AS3: 4.5106 | AT3: 4.9631 | AU3: =AT3/100 -> 0.049631 | AV3: =AVERAGE(AI3:AT3)/100 -> 0.030922643 | AY3: 0 | AZ3: 5.014 | BA3: 5.53318 | BB3: 5.179769 | BC3: 5.433642 | BD3: 5.582 | BE3: 5.5747 | BF3: 5.8372 | BG3: 6.1487 | BH3: 5.9749 | BI3: 6.275 | BJ3: 6.3221 | BK3: 6.3389 | BL3: =BK3/100 -> 0.063389 | BM3: =AVERAGE(AZ3:BK3)/100 -> 0.057678409 | BO3: 0 | BP3: 6.1856 | BQ3: 6.0754 | BR3: 5.8214 | BS3: 5.5406 | BT3: 5.5879 | BU3: 5.4864 | BV3: 5.8591 | BW3: 6.3492 | BX3: 5.9904 | BY3: 5.9945 | BZ3: 6.254 | CA3: 6.716 | CB3: =CA3/100 -> 0.06716 | CC3: =AVERAGE(BP3:CA3)/100 -> 0.05988375 | CE3: 0 | CF3: 6.332542 | CG3: 6.29575 | CH3: 6.391375 | CI3: 6.273421 | CJ3: 6.115364 | CK3: 5.858857 | CL3: 5.586246 | CM3: 5.165326 | CN3: 4.957132 | CO3: 4.764311 | CP3: 4.809692 | CQ3: 4.744445 | CR3: =CQ3/100 -> 0.04744445 | CS3: =AVERAGE(CF3:CQ3)/100 -> 0.056078717
B4: 1 | C4: 4.9931 | D4: 4.7606 | E4: 5.3178 | F4: 5.452 | G4: 5.3735 | H4: 4.8661 | I4: 4.2655 | J4: 4.04385 | K4: 3.8222 | L4: 3.6421 | M4: 3.2591 | N4: 3.6411 | O4: =N4/100 -> 0.036411 | P4: =AVERAGE(C4:N4)/100 -> 0.044530792 | R4: 1 | S4: 3.9861 | T4: 4.1028 | U4: 4.1295 | V4: 3.9787 | W4: 3.8295 | X4: 3.6914 | Y4: 3.3593 | Z4: 3.2319 | AA4: 3.4862 | AB4: 3.5529 | AC4: 3.4599 | AD4: 3.3927 | AE4: =AD4/100 -> 0.033927 | AF4: =AVERAGE(S4:AD4)/100 -> 0.036834083 | AH4: 1 | AI4: 3.362584 | AJ4: 3.2041 | AK4: 3.4793 | AL4: 4.173886 | AM4: 4.2987 | AN4: 4.264 | AO4: 4.391 | AP4: 4.9415 | AQ4: 5.7408 | AR4: 6.1083 | AS4: 5.7607 | AT4: 5.5201 | AU4: =AT4/100 -> 0.055201 | AV4: =AVERAGE(AI4:AT4)/100 -> 0.046037475 | AY4: 1 | AZ4: 5.5977 | BA4: 6.0982 | BB4: 5.850129 | BC4: 5.939598 | BD4: 5.6808 | BE4: 5.6723 | BF4: 5.8592 | BG4: 6.1605 | BH4: 6.18 | BI4: 6.7025 | BJ4: 6.4456 | BK4: 6.3682 | BL4: =BK4/100 -> 0.063682 | BM4: =AVERAGE(AZ4:BK4)/100 -> 0.060462273 | BO4: 1 | BP4: 6.2475 | BQ4: 6.1918 | BR4: 6.1034 | BS4: 6.6692 | BT4: 6.3036 | BU4: 6.5464 | BV4: 6.3128 | BW4: 6.3811 | BX4: 6.0798 | BY4: 6.3031 | BZ4: 6.4589 | CA4: 6.879 | CB4: =CA4/100 -> 0.06879 | CC4: =AVERAGE(BP4:CA4)/100 -> 0.0637305 | CE4: 1 | CF4: 6.733097 | CG4: 6.532179 | CH4: 6.682739 | CI4: 6.440293 | CJ4: 6.298267 | CK4: 6.060756 | CL4: 5.806852 | CM4: 5.37152 | CN4: 5.125593 | CO4: 4.977302 | CP4: 5.10608 | CQ4: 5.042045 | CR4: =CQ4/100 -> 0.05042045 | CS4: =AVERAGE(CF4:CQ4)/100 -> 0.058480603
B5: 2 | C5: 5.4854 | D5: 5.2622 | E5: 6.2345 | F5: 6.2966 | G5: 6.2696 | H5: 5.6839 | I5: 4.9523 | J5: 4.7645 | K5: 4.5767 | L5: 4.3922 | M5: 4.1544 | N5: 4.2282 | O5: =N5/100 -> 0.042282 | P5: =AVERAGE(C5:N5)/100 -> 0.051917083 | R5: 2 | S5: 4.5259 | T5: 4.6967 | U5: 4.8224 | V5: 4.6419 | W5: 4.475 | X5: 4.3658 | Y5: 4.1074 | Z5: 4.0132 | AA5: 4.179 | AB5: 4.1169 | AC5: 3.9663 | AD5: 3.9651 | AE5: =AD5/100 -> 0.039651 | AF5: =AVERAGE(S5:AD5)/100 -> 0.043229667 | AH5: 2 | AI5: 4.042307 | AJ5: 4.0393 | AK5: 4.2977 | AL5: 5.14708 | AM5: 5.1219 | AN5: 5.0706 | AO5: 5.5323 | AP5: 5.7956 | AQ5: 6.292 | AR5: 6.7947 | AS5: 6.2666 | AT5: 5.9315 | AU5: =AT5/100 -> 0.059315 | AV5: =AVERAGE(AI5:AT5)/100 -> 0.053609656 | AY5: 2 | AZ5: 5.9402 | BA5: 6.3434 | BB5: 6.163323 | BC5: 6.14506 | BD5: 5.7907 | BE5: 5.7694 | BF5: 5.9002 | BG5: 6.1732 | BH5: 6.2768 | BI5: 6.9136 | BJ5: 6.5334 | BK5: 6.3972 | BL5: =BK5/100 -> 0.063972 | BM5: =AVERAGE(AZ5:BK5)/100 -> 0.061955403 | BO5: 2 | BP5: 6.3026 | BQ5: 6.2853 | BR5: 6.295 | BS5: 6.9963 | BT5: 6.6292 | BU5: 6.7424 | BV5: 6.545 | BW5: 6.4187 | BX5: 6.1414 | BY5: 6.4529 | BZ5: 6.5863 | CA5: 6.9495 | CB5: =CA5/100 -> 0.069495 | CC5: =AVERAGE(BP5:CA5)/100 -> 0.065287167 | CE5: 2 | CF5: 6.882736 | CG5: 6.68675 | CH5: 6.784758 | CI5: 6.533985 | CJ5: 6.387348 | CK5: 6.221656 | CL5: 5.991938 | CM5: 5.564964 | CN5: 5.283589 | CO5: 5.20273 | CP5: 5.446501 | CQ5: 5.347214 | CR5: =CQ5/100 -> 0.05347214 | CS5: =AVERAGE(CF5:CQ5)/100 -> 0.060278474
B6: 3 | C6: 5.8049 | D6: 5.6548 | E6: 6.8052 | F6: 6.8631 | G6: 6.6531 | H6: 6.143 | I6: 5.4551 | J6: 5.29075 | K6: 5.1264 | L6: 4.9516 | M6: 4.7041 | N6: 4.6811 | O6: =N6/100 -> 0.046811 | P6: =AVERAGE(C6:N6)/100 -> 0.056777625 | R6: 3 | S6: 4.8904 | T6: 5.1518 | U6: 5.3296 | V6: 5.1298 | W6: 4.9686 | X6: 4.8606 | Y6: 4.6028 | Z6: 4.5358 | AA6: 4.6248 | AB6: 4.5563 | AC6: 4.4378 | AD6: 4.4823 | AE6: =AD6/100 -> 0.044823 | AF6: =AVERAGE(S6:AD6)/100 -> 0.0479755 | AH6: 3 | AI6: 4.633574 | AJ6: 4.6788 | AK6: 4.9083 | AL6: 5.711204 | AM6: 5.719 | AN6: 5.6937 | AO6: 6.1033 | AP6: 6.1714 | AQ6: 6.548 | AR6: 7.01 | AS6: 6.4797 | AT6: 6.2163 | AU6: =AT6/100 -> 0.062163 | AV6: =AVERAGE(AI6:AT6)/100 -> 0.058227732 | AY6: 3 | AZ6: 6.1318 | BA6: 6.4164 | BB6: 6.298712 | BC6: 6.225046 | BD6: 5.899 | BE6: 5.8592 | BF6: 5.9523 | BG6: 6.1927 | BH6: 6.3541 | BI6: 7.0141 | BJ6: 6.5903 | BK6: 6.4245 | BL6: =BK6/100 -> 0.064245 | BM6: =AVERAGE(AZ6:BK6)/100 -> 0.062798465 | BO6: 3 | BP6: 6.3512 | BQ6: 6.3573 | BR6: 6.4145 | BS6: 7.065 | BT6: 6.7531 | BU6: 6.8071 | BV6: 6.6553 | BW6: 6.4573 | BX6: 6.1877 | BY6: 6.5327 | BZ6: 6.6665 | CA6: 6.9768 | CB6: =CA6/100 -> 0.069768 | CC6: =AVERAGE(BP6:CA6)/100 -> 0.066020417 | CE6: 3 | CF6: 6.954089 | CG6: 6.796479 | CH6: 6.86482 | CI6: 6.629536 | CJ6: 6.490994 | CK6: 6.36137 | CL6: 6.161431 | CM6: 5.746777 | CN6: 5.473168 | CO6: 5.413157 | CP6: 5.716022 | CQ6: 5.591021 | CR6: =CQ6/100 -> 0.05591021 | CS6: =AVERAGE(CF6:CQ6)/100 -> 0.061832387
B7: 4 | C7: 6.0356 | D7: 5.9834 | E7: 7.1952 | F7: 7.2467 | G7: 6.8376 | H7: 6.4352 | I7: 5.8391 | J7: 5.69885 | K7: 5.5586 | L7: 5.3922 | M7: 5.0851 | N7: 5.0367 | O7: =N7/100 -> 0.050367 | P7: =AVERAGE(C7:N7)/100 -> 0.060286875 | R7: 4 | S7: 5.1789 | T7: 5.5152 | U7: 5.7139 | V7: 5.501 | W7: 5.3539 | X7: 5.2509 | Y7: 4.9775 | Z7: 4.9188 | AA7: 4.9688 | AB7: 4.9236 | AC7: 4.8627 | AD7: 4.9389 | AE7: =AD7/100 -> 0.049389 | AF7: =AVERAGE(S7:AD7)/100 -> 0.051753417 | AH7: 4 | AI7: 5.133759 | AJ7: 5.1808 | AK7: 5.3987 | AL7: 6.093273 | AM7: 6.1617 | AN7: 6.1707 | AO7: 6.4486 | AP7: 6.4723 | AQ7: 6.7752 | AR7: 7.1509 | AS7: 6.6155 | AT7: 6.4225 | AU7: =AT7/100 -> 0.064225 | AV7: =AVERAGE(AI7:AT7)/100 -> 0.06168661 | AY7: 4 | AZ7: 6.2553 | BA7: 6.4723 | BB7: 6.376422 | BC7: 6.279659 | BD7: 6.0028 | BE7: 5.943 | BF7: 6.0106 | BG7: 6.2209 | BH7: 6.4396 | BI7: 7.0706 | BJ7: 6.6287 | BK7: 6.4507 | BL7: =BK7/100 -> 0.064507 | BM7: =AVERAGE(AZ7:BK7)/100 -> 0.063458817 | BO7: 4 | BP7: 6.397 | BQ7: 6.4163 | BR7: 6.4928 | BS7: 7.08 | BT7: 6.8016 | BU7: 6.8754 | BV7: 6.7174 | BW7: 6.4957 | BX7: 6.2304 | BY7: 6.593 | BZ7: 6.7254 | CA7: 6.9912 | CB7: =CA7/100 -> 0.069912 | CC7: =AVERAGE(BP7:CA7)/100 -> 0.0665135 | CE7: 4 | CF7: 7.021155 | CG7: 6.887928 | CH7: 6.964598 | CI7: 6.731358 | CJ7: 6.60972 | CK7: 6.493439 | CL7: 6.324495 | CM7: 5.931117 | CN7: 5.695081 | CO7: 5.616053 | CP7: 5.939032 | CQ7: 5.803501 | CR7: =CQ7/100 -> 0.05803501 | CS7: =AVERAGE(CF7:CQ7)/100 -> 0.063347897
B8: 5 | C8: 6.222 | D8: 6.268 | E8: 7.4822 | F8: 7.5101 | G8: 6.9622 | H8: 6.6519 | I8: 6.1438 | J8: 6.0299 | K8: 5.916 | L8: 5.7532 | M8: 5.3845 | N8: 5.3215 | O8: =N8/100 -> 0.053215 | P8: =AVERAGE(C8:N8)/100 -> 0.06303775 | R8: 5 | S8: 4.4328 | T8: 5.814 | U8: 6.0155 | V8: 5.7935 | W8: 5.6616 | X8: 5.576 | Y8: 5.2921 | Z8: 5.2253 | AA8: 5.2702 | AB8: 5.2442 | AC8: 5.2369 | AD8: 5.3344 | AE8: =AD8/100 -> 0.053344 | AF8: =AVERAGE(S8:AD8)/100 -> 0.054080417 | AH8: 5 | AI8: 5.548205 | AJ8: 5.5803 | AK8: 5.803 | AL8: 6.381229 | AM8: 6.4956 | AN8: 6.5329 | AO8: 6.6944 | AP8: 6.7174 | AQ8: 6.9795 | AR8: 7.2775 | AS8: 6.733 | AT8: 6.5785 | AU8: =AT8/100 -> 0.065785 | AV8: =AVERAGE(AI8:AT8)/100 -> 0.064434612 | AY8: 5 | AZ8: 6.3506 | BA8: 6.546 | BB8: 6.443568 | BC8: 6.341436 | BD8: 6.1002 | BE8: 6.0216 | BF8: 6.0715 | BG8: 6.2566 | BH8: 6.5309 | BI8: 7.1085 | BJ8: 6.6566 | BK8: 6.4763 | BL8: =BK8/100 -> 0.064763 | BM8: =AVERAGE(AZ8:BK8)/100 -> 0.064086503 | BO8: 5 | BP8: 6.4413 | BQ8: 6.4673 | BR8: 6.5482 | BS8: 7.089 | BT8: 6.8265 | BU8: 6.9404 | BV8: 6.763 | BW8: 6.5329 | BX8: 6.2742 | BY8: 6.6494 | BZ8: 6.7743 | CA8: 7.0037 | CB8: =CA8/100 -> 0.070037 | CC8: =AVERAGE(BP8:CA8)/100 -> 0.066925167 | CE8: 5 | CF8: 7.097502 | CG8: 6.970384 | CH8: 7.075234 | CI8: 6.835578 | CJ8: 6.734048 | CK8: 6.620184 | CL8: 6.479197 | CM8: 6.117256 | CN8: 5.934388 | CO8: 5.810166 | CP8: 6.126395 | CQ8: 5.992786 | CR8: =CQ8/100 -> 0.05992786 | CS8: =AVERAGE(CF8:CQ8)/100 -> 0.064827598
B9: 6 | C9: 6.3856 | D9: 6.5165 | E9: 7.7035 | F9: 7.6938 | G9: 7.0797 | H9: 6.8333 | I9: 6.3929 | J9: 6.30605 | K9: 6.2192 | L9: 6.0559 | M9: 5.6421 | N9: 5.5542 | O9: =N9/100 -> 0.055542 | P9: =AVERAGE(C9:N9)/100 -> 0.065318958 | R9: 6 | S9: 5.6661 | T9: 6.0645 | U9: 6.2597 | V9: 6.0316 | W9: 5.9128 | X9: 5.8553 | Y9: 5.5717 | Z9: 5.4867 | AA9: 5.548 | AB9: 5.5297 | AC9: 5.5606 | AD9: 5.6716 | AE9: =AD9/100 -> 0.056716 | AF9: =AVERAGE(S9:AD9)/100 -> 0.057631917 | AH9: 6 | AI9: 5.886127 | AJ9: 5.9002 | AK9: 6.1357 | AL9: 6.608339 | AM9: 6.7507 | AN9: 6.8062 | AO9: 6.8842 | AP9: 6.8956 | AQ9: 7.142 | AR9: 7.3849 | AS9: 6.8407 | AT9: 6.7012 | AU9: =AT9/100 -> 0.067012 | AV9: =AVERAGE(AI9:AT9)/100 -> 0.066613222 | AY9: 6 | AZ9: 6.4345 | BA9: 6.6334 | BB9: 6.514002 | BC9: 6.414802 | BD9: 6.1902 | BE9: 6.0954 | BF9: 6.1325 | BG9: 6.2979 | BH9: 6.6196 | BI9: 7.1369 | BJ9: 6.6788 | BK9: 6.5016 | BL9: =BK9/100 -> 0.065016 | BM9: =AVERAGE(AZ9:BK9)/100 -> 0.064708003 | BO9: 6 | BP9: 6.4846 | BQ9: 6.5129 | BR9: 6.5915 | BS9: 7.0986 | BT9: 6.8464 | BU9: 6.9904 | BV9: 6.8036 | BW9: 6.5681 | BX9: 6.3207 | BY9: 6.7043 | BZ9: 6.8176 | CA9: 7.0171 | CB9: =CA9/100 -> 0.070171 | CC9: =AVERAGE(BP9:CA9)/100 -> 0.0672965 | CE9: 6 | CF9: 7.178213 | CG9: 7.046001 | CH9: 7.181579 | CI9: 6.936801 | CJ9: 6.854373 | CK9: 6.740155 | CL9: 6.621577 | CM9: 6.299816 | CN9: 6.174263 | CO9: 5.992455 | CP9: 6.284249 | CQ9: 6.160409 | CR9: =CQ9/100 -> 0.06160409 | CS9: =AVERAGE(CF9:CQ9)/100 -> 0.066224909
B10: 7 | C10: 6.5361 | D10: 6.7325 | E10: 7.8776 | F10: 7.8244 | G10: 7.2037 | H10: 6.9949 | I10: 6.6011 | J10: 6.5397 | K10: 6.4783 | L10: 6.3125 | M10: 5.8736 | N10: 5.7483 | O10: =N10/100 -> 0.057483 | P10: =AVERAGE(C10:N10)/100 -> 0.067268917 | R10: 7 | S10: 5.8811 | T10: 6.2767 | U10: 6.4625 | V10: 6.2307 | W10: 6.1223 | X10: 6.0986 | Y10: 5.8245 | Z10: 5.718 | AA10: 5.805 | AB10: 5.7847 | AC10: 5.8368 | AD10: 5.9554 | AE10: =AD10/100 -> 0.059554 | AF10: =AVERAGE(S10:AD10)/100 -> 0.059996917 | AH10: 7 | AI10: 6.158132 | AJ10: 6.1563 | AK10: 6.4057 | AL10: 6.788419 | AM10: 6.9472 | AN10: 7.0113 | AO10: 7.0333 | AP10: 7.0129 | AQ10: 7.2584 | AR10: 7.4669 | AS10: 6.9353 | AT10: 6.8004 | AU10: =AT10/100 -> 0.068004 | AV10: =AVERAGE(AI10:AT10)/100 -> 0.068311876 | AY10: 7 | AZ10: 6.5131 | BA10: 6.7229 | BB10: 6.588127 | BC10: 6.494662 | BD10: 6.2724 | BE10: 6.1646 | BF10: 6.1918 | BG10: 6.3423 | BH10: 6.6991 | BI10: 7.1592 | BJ10: 6.6985 | BK10: 6.5265 | BL10: =BK10/100 -> 0.065265 | BM10: =AVERAGE(AZ10:BK10)/100 -> 0.065310991 | BO10: 7 | BP10: 6.5267 | BQ10: 6.5548 | BR10: 6.6285 | BS10: 7.1077 | BT10: 6.8662 | BU10: 7.0238 | BV10: 6.8422 | BW10: 6.601 | BX10: 6.3692 | BY10: 6.7558 | BZ10: 6.8566 | CA10: 7.0312 | CB10: =CA10/100 -> 0.070312 | CC10: =AVERAGE(BP10:CA10)/100 -> 0.067636417 | CE10: 7 | CF10: 7.255584 | CG10: 7.11436 | CH10: 7.273442 | CI10: 7.030351 | CJ10: 6.964117 | CK10: 6.85137 | CL10: 6.749052 | CM10: 6.473023 | CN10: 6.401576 | CO10: 6.160062 | CP10: 6.416817 | CQ10: 6.306901 | CR10: =CQ10/100 -> 0.06306901 | CS10: =AVERAGE(CF10:CQ10)/100 -> 0.067497213
B11: 8 | C11: 6.6765 | D11: 6.9182 | E11: 8.0152 | F11: 7.9192 | G11: 7.3325 | H11: 7.141 | I11: 6.7773 | J11: 6.73815 | K11: 6.699 | L11: 6.5304 | M11: 6.0841 | N11: 5.9132 | O11: =N11/100 -> 0.059132 | P11: =AVERAGE(C11:N11)/100 -> 0.068953958 | R11: 8 | S11: 6.0763 | T11: 6.4569 | U11: 6.6343 | V11: 6.4009 | W11: 6.3002 | X11: 6.3109 | Y11: 6.0522 | Z11: 5.9253 | AA11: 6.0387 | AB11: 6.0112 | AC11: 6.07 | AD11: 6.1915 | AE11: =AD11/100 -> 0.061915 | AF11: =AVERAGE(S11:AD11)/100 -> 0.062057 | AH11: 8 | AI11: 6.374777 | AJ11: 6.3607 | AK11: 6.6207 | AL11: 6.929333 | AM11: 7.0994 | AN11: 7.1644 | AO11: 7.1489 | AP11: 7.0848 | AQ11: 7.3359 | AR11: 7.5244 | AS11: 7.0136 | AT11: 6.8823 | AU11: =AT11/100 -> 0.068823 | AV11: =AVERAGE(AI11:AT11)/100 -> 0.069616008 | AY11: 8 | AZ11: 6.5875 | BA11: 6.8052 | BB11: 6.662206 | BC11: 6.574432 | BD11: 6.3467 | BE11: 6.2293 | BF11: 6.2482 | BG11: 6.3877 | BH11: 6.7662 | BI11: 7.1767 | BJ11: 6.7171 | BK11: 6.5511 | BL11: =BK11/100 -> 0.065511 | BM11: =AVERAGE(AZ11:BK11)/100 -> 0.065876948 | BO11: 8 | BP11: 6.5673 | BQ11: 6.5935 | BR11: 6.6621 | BS11: 7.115 | BT11: 6.886 | BU11: 7.0442 | BV11: 6.8788 | BW11: 6.6312 | BX11: 6.4186 | BY11: 6.8022 | BZ11: 6.8913 | CA11: 7.0451 | CB11: =CA11/100 -> 0.070451 | CC11: =AVERAGE(BP11:CA11)/100 -> 0.067946083 | CE11: 8 | CF11: 7.32446 | CG11: 7.174857 | CH11: 7.346833 | CI11: 7.113692 | CJ11: 7.060061 | CK11: 6.951996 | CL11: 6.860609 | CM11: 6.632584 | CN11: 6.607722 | CO11: 6.311513 | CP11: 6.527736 | CQ11: 6.433372 | CR11: =CQ11/100 -> 0.06433372 | CS11: =AVERAGE(CF11:CQ11)/100 -> 0.068621196
B12: 9 | C12: 6.8073 | D12: 7.0757 | E12: 8.1233 | F12: 7.9895 | G12: 7.4597 | H12: 7.2722 | I12: 6.9274 | J12: 6.90645 | K12: 6.8855 | L12: 6.7148 | M12: 6.2742 | N12: 6.0556 | O12: =N12/100 -> 0.060556 | P12: =AVERAGE(C12:N12)/100 -> 0.070409708 | R12: 9 | S12: 6.2498 | T12: 6.61 | U12: 6.7815 | V12: 6.5484 | W12: 6.4536 | X12: 6.4952 | Y12: 6.2545 | Z12: 6.1111 | AA12: 6.2464 | AB12: 6.2105 | AC12: 6.265 | AD12: 6.3861 | AE12: =AD12/100 -> 0.063861 | AF12: =AVERAGE(S12:AD12)/100 -> 0.063843417 | AH12: 9 | AI12: 6.545812 | AJ12: 6.523 | AK12: 6.7889 | AL12: 7.037461 | AM12: 7.2176 | AN12: 7.2781 | AO12: 7.2365 | AP12: 7.1266 | AQ12: 7.3847 | AR12: 7.5624 | AS12: 7.0752 | AT12: 6.9505 | AU12: =AT12/100 -> 0.069505 | AV12: =AVERAGE(AI12:AT12)/100 -> 0.070605644 | AY12: 9 | AZ12: 6.6569 | BA12: 6.8756 | BB12: 6.732297 | BC12: 6.648953 | BD12: 6.4132 | BE12: 6.2893 | BF12: 6.301 | BG12: 6.4323 | BH12: 6.8201 | BI12: 7.1901 | BJ12: 6.7355 | BK12: 6.5753 | BL12: =BK12/100 -> 0.065753 | BM12: =AVERAGE(AZ12:BK12)/100 -> 0.066392125 | BO12: 9 | BP12: 6.6058 | BQ12: 6.6293 | BR12: 6.6938 | BS12: 7.1202 | BT12: 6.9048 | BU12: 7.0559 | BV12: 6.9123 | BW12: 6.6587 | BX12: 6.4675 | BY12: 6.842 | BZ12: 6.9218 | CA12: 7.058 | CB12: =CA12/100 -> 0.07058 | CC12: =AVERAGE(BP12:CA12)/100 -> 0.068225083 | CE12: 9 | CF12: 7.382217 | CG12: 7.227226 | CH12: 7.402076 | CI12: 7.185386 | CJ12: 7.14093 | CK12: 7.041377 | CL12: 6.956446 | CM12: 6.775677 | CN12: 6.788092 | CO12: 6.446304 | CP12: 6.620494 | CQ12: 6.541792 | CR12: =CQ12/100 -> 0.06541792 | CS12: =AVERAGE(CF12:CQ12)/100 -> 0.069590014
B13: 10 | C13: 6.9278 | D13: 7.2075 | E13: 8.2074 | F13: 8.0427 | G13: 7.5793 | H13: 7.388 | I13: 7.0555 | J13: 7.04835 | K13: 7.0412 | L13: 6.8699 | M13: 6.4434 | N13: 6.1801 | O13: =N13/100 -> 0.061801 | P13: =AVERAGE(C13:N13)/100 -> 0.071659292 | R13: 10 | S13: 6.401 | T13: 6.7394 | U13: 6.9087 | V13: 6.6774 | W13: 6.5874 | X13: 6.6539 | Y13: 6.4313 | Z13: 6.2764 | AA13: 6.4266 | AB13: 6.3839 | AC13: 6.4269 | AD13: 6.545 | AE13: =AD13/100 -> 0.06545 | AF13: =AVERAGE(S13:AD13)/100 -> 0.065381583 | AH13: 10 | AI13: 6.679829 | AJ13: 6.651 | AK13: 6.9183 | AL13: 7.118748 | AM13: 7.3093 | AN13: 7.3623 | AO13: 7.3011 | AP13: 7.1498 | AQ13: 7.4142 | AR13: 7.5862 | AS13: 7.1218 | AT13: 7.0077 | AU13: =AT13/100 -> 0.070077 | AV13: =AVERAGE(AI13:AT13)/100 -> 0.071350231 | AY13: 10 | AZ13: 6.7202 | BA13: 6.9326 | BB13: 6.795604 | BC13: 6.71512 | BD13: 6.4724 | BE13: 6.3449 | BF13: 6.3498 | BG13: 6.4748 | BH13: 6.862 | BI13: 7.2002 | BJ13: 6.754 | BK13: 6.5991 | BL13: =BK13/100 -> 0.065991 | BM13: =AVERAGE(AZ13:BK13)/100 -> 0.066850603 | BO13: 10 | BP13: 6.642 | BQ13: 6.6625 | BR13: 6.7239 | BS13: 7.1237 | BT13: 6.9215 | BU13: 7.0623 | BV13: 6.942 | BW13: 6.6834 | BX13: 6.5146 | BY13: 6.875 | BZ13: 6.948 | CA13: 7.0694 | CB13: =CA13/100 -> 0.070694 | CC13: =AVERAGE(BP13:CA13)/100 -> 0.068473583 | CE13: 10 | CF13: 7.428425 | CG13: 7.271478 | CH13: 7.441514 | CI13: 7.24547 | CJ13: 7.207356 | CK13: 7.119276 | CL13: 7.037663 | CM13: 6.901062 | CN13: 6.941407 | CO13: 6.564848 | CP13: 6.698136 | CQ13: 6.634413 | CR13: =CQ13/100 -> 0.06634413 | CS13: =AVERAGE(CF13:CQ13)/100 -> 0.070409207
B14: 11 | C14: 7.0373 | D14: 7.3163 | E14: 8.272 | F14: 8.0837 | G14: 7.6872 | H14: 7.4882 | I14: 7.1647 | J14: 7.1673 | K14: 7.1699 | L14: 6.9994 | M14: 6.5917 | N14: 6.2901 | O14: =N14/100 -> 0.062901 | P14: =AVERAGE(C14:N14)/100 -> 0.072723167 | R14: 11 | S14: 6.5301 | T14: 6.8483 | U14: 7.0188 | V14: 6.7907 | W14: 6.7051 | X14: 6.7892 | Y14: 6.5831 | Z14: 6.4218 | AA14: 6.5797 | AB14: 6.5331 | AC14: 6.5604 | AD14: 6.674 | AE14: =AD14/100 -> 0.06674 | AF14: =AVERAGE(S14:AD14)/100 -> 0.06669525 | AH14: 11 | AI14: 6.784161 | AJ14: 6.7513 | AK14: 7.0162 | AL14: 7.178695 | AM14: 7.3805 | AN14: 7.4243 | AO14: 7.3478 | AP14: 7.1624 | AQ14: 7.4314 | AR14: 7.6007 | AS14: 7.1558 | AT14: 7.0555 | AU14: =AT14/100 -> 0.070555 | AV14: =AVERAGE(AI14:AT14)/100 -> 0.071907297 | AY14: 11 | AZ14: 6.7767 | BA14: 6.9768 | BB14: 6.850667 | BC14: 6.771617 | BD14: 6.5248 | BE14: 6.3961 | BF14: 6.3945 | BG14: 6.5144 | BH14: 6.8936 | BI14: 7.2075 | BJ14: 6.7725 | BK14: 6.6223 | BL14: =BK14/100 -> 0.066223 | BM14: =AVERAGE(AZ14:BK14)/100 -> 0.067251237 | BO14: 11 | BP14: 6.6756 | BQ14: 6.693 | BR14: 6.7525 | BS14: 7.1258 | BT14: 6.9357 | BU14: 7.0657 | BV14: 6.962 | BW14: 6.7054 | BX14: 6.5591 | BY14: 6.9017 | BZ14: 6.9702 | CA14: 7.0789 | CB14: =CA14/100 -> 0.070789 | CC14: =AVERAGE(BP14:CA14)/100 -> 0.068688 | CE14: 11 | CF14: 7.428425 | CG14: 7.271478 | CH14: 7.441514 | CI14: 7.24547 | CJ14: 7.207356 | CK14: 7.119276 | CL14: 7.037663 | CM14: 6.901062 | CN14: 6.941407 | CO14: 6.564848 | CP14: 6.698136 | CQ14: 6.634413 | CR14: =CQ14/100 -> 0.06634413 | CS14: =AVERAGE(CF14:CQ14)/100 -> 0.070409207
... B33: 30 | C33: 7.6644 | D33: 7.7305 | E33: 8.4567 | F33: 8.2449 | G33: 8.166 | H33: 7.9145 | I33: 7.6953 | J33: 7.6798 | K33: 7.6643 | L33: 7.539 | M33: 7.2827 | N33: 7.1018 | O33: =N33/100 -> 0.071018 | P33: =AVERAGE(C33:N33)/100 -> 0.077616583 | R33: 30 | S33: 7.065 | T33: 7.3337 | U33: 7.6331 | V33: 7.4808 | W33: 7.5093 | X33: 7.3956 | Y33: 7.238 | Z33: 7.1564 | AA33: 7.1902 | AB33: 7.2234 | AC33: 7.1196 | AD33: 7.1638 | AE33: =AD33/100 -> 0.071638 | AF33: =AVERAGE(S33:AD33)/100 -> 0.072924083 | AH33: 30 | AI33: 7.122366 | AJ33: 7.078 | AK33: 7.2789 | AL33: 7.322221 | AM33: 7.6131 | AN33: 7.5918 | AO33: 7.4503 | AP33: 7.1758 | AQ33: 7.4531 | AR33: 7.6203 | AS33: 7.2305 | AT33: 7.2692 | AU33: =AT33/100 -> 0.072692 | AV33: =AVERAGE(AI33:AT33)/100 -> 0.073504656 | AY33: 30 | AZ33: 7.0467 | BA33: 7.092 | BB33: 7.067553 | BC33: 6.978269 | BD33: 6.8432 | BE33: 6.7893 | BF33: 6.712 | BG33: 6.7631 | BH33: 6.9725 | BI33: 7.2245 | BJ33: 6.9807 | BK33: 6.8877 | BL33: =BK33/100 -> 0.068877 | BM33: =AVERAGE(AZ33:BK33)/100 -> 0.069464602 | BO33: 30 | BP33: 6.9097 | BQ33: 6.9055 | BR33: 6.9691 | BS33: 7.1289 | BT33: 6.9831 | BU33: 7.0691 | BV33: 7.0647 | BW33: 6.8404 | BX33: 6.8586 | BY33: 6.9835 | BZ33: 7.0564 | CA33: 7.1118 | CB33: =CA33/100 -> 0.071118 | CC33: =AVERAGE(BP33:CA33)/100 -> 0.069900667 | CE33: 30 | CF33: 7.428425 | CG33: 7.271478 | CH33: 7.441514 | CI33: 7.24547 | CJ33: 7.207356 | CK33: 7.119276 | CL33: 7.037663 | CM33: 6.901062 | CN33: 6.941407 | CO33: 6.564848 | CP33: 6.698136 | CQ33: 6.634413 | CR33: =CQ33/100 -> 0.06634413 | CS33: =AVERAGE(CF33:CQ33)/100 -> 0.070409207

Sheet Inflasi
A2: Bulan | B2: Tahun | C2: Inflasi | F2: Valuasi | G2: Inflasi Rata-Rata 3 Tahun
A3: Desember | B3: 2025 | C3: 0.0292 | F3: 31 Des 2020 | G3: =AVERAGE(C63:C98) -> 0.027541667
A4: November | B4: 2025 | C4: 0.0272 | F4: 31 Des 2021 | G4: =AVERAGE(C51:C86) -> 0.022081667
A5: Oktober | B5: 2025 | C5: 0.0286 | F5: 31 Des 2022 | G5: =AVERAGE(C39:C74) -> 0.026003889
A6: September | B6: 2025 | C6: 0.0265 | F6: 31 Des 2023 | G6: =AVERAGE(C27:C62) -> 0.031503889
A7: Agustus | B7: 2025 | C7: 0.0231 | F7: 31 Des 2024 | G7: =AVERAGE(C15:C50) -> 0.033983333
A8: Juli | B8: 2025 | C8: 0.0237 | F8: 31 Des 2025 | G8: =AVERAGE(C3:C38) -> 0.026338889
A9: Juni | B9: 2025 | C9: 0.0187
A10: Mei | B10: 2025 | C10: 0.016
A11: April | B11: 2025 | C11: 0.0195
A12: Maret | B12: 2025 | C12: 0.0103
A13: Februari | B13: 2025 | C13: -0.0009
A14: Januari | B14: 2025 | C14: 0.0076
A15: Desember | B15: 2024 | C15: 0.0157
A16: November | B16: 2024 | C16: 0.0155
A17: Oktober | B17: 2024 | C17: 0.0171
A18: September | B18: 2024 | C18: 0.0184
A19: Agustus | B19: 2024 | C19: 0.0212
A20: Juli | B20: 2024 | C20: 0.0213
... A98: Januari | B98: 2018 | C98: 0.0325

Sheet Lapse Rasio
B2: [Lapse Rasio]
B3: Year | C3: 2020 | D3: 2021 | E3: 2022 | F3: 2023 | G3: 2024 | H3: 2025
B4: 1 | C4: 0 | D4: 0 | E4: 0 | F4: 0 | G4: 0 | H4: 0
B5: =B4+1 -> 2 | C5: 0 | D5: 0 | E5: 0 | F5: 0 | G5: 0 | H5: 0
B6: =B5+1 -> 3 | C6: 0 | D6: 0 | E6: 0 | F6: 0 | G6: 0 | H6: 0
B7: =B6+1 -> 4 | C7: 0 | D7: 0 | E7: 0 | F7: 0 | G7: 0 | H7: 0
B8: =B7+1 -> 5 | C8: 0 | D8: 0 | E8: 0 | F8: 0 | G8: 0 | H8: 0
B9: =B8+1 -> 6 | C9: 0 | D9: 0 | E9: 0 | F9: 0 | G9: 0 | H9: 0
B10: =B9+1 -> 7 | C10: 0 | D10: 0 | E10: 0 | F10: 0 | G10: 0 | H10: 0
B11: =B10+1 -> 8 | C11: 0 | D11: 0 | E11: 0 | F11: 0 | G11: 0 | H11: 0
B12: =B11+1 -> 9 | C12: 0 | D12: 0 | E12: 0 | F12: 0 | G12: 0 | H12: 0
B13: 10 | C13: 0 | D13: 0 | E13: 0 | F13: 0 | G13: 0 | H13: 0
B14: 11 | C14: 0 | D14: 0 | E14: 0 | F14: 0 | G14: 0 | H14: 0
B15: 12 | C15: 0 | D15: 0 | E15: 0 | F15: 0 | G15: 0 | H15: 0
B16: 13 | C16: 0 | D16: 0 | E16: 0 | F16: 0 | G16: 0 | H16: 0
B17: 14 | C17: 0 | D17: 0 | E17: 0 | F17: 0 | G17: 0 | H17: 0
B18: 15 | C18: 0 | D18: 0 | E18: 0 | F18: 0 | G18: 0 | H18: 0
B19: 16 | C19: 0 | D19: 0 | E19: 0 | F19: 0 | G19: 0 | H19: 0
B20: 17 | C20: 0 | D20: 0 | E20: 0 | F20: 0 | G20: 0 | H20: 0
B21: 18 | C21: 0 | D21: 0 | E21: 0 | F21: 0 | G21: 0 | H21: 0
B22: 19 | C22: 0 | D22: 0 | E22: 0 | F22: 0 | G22: 0 | H22: 0
B23: 20 | C23: 0 | D23: 0 | E23: 0 | F23: 0 | G23: 0 | H23: 0
B24: 21 | C24: 0 | D24: 0 | E24: 0 | F24: 0 | G24: 0 | H24: 0
... B43: 40 | C43: 0 | D43: 0 | E43: 0 | F43: 0 | G43: 0 | H43: 0

Sheet Expense Rasio
D3: 2020 | E3: 2021 | F3: =E3+1 -> 2022 | G3: =F3+1 -> 2023 | H3: =G3+1 -> 2024 | I3: =H3+1 -> 2025
B4: Premi Bruto | D4: =D5+D6-D7 -> 631220.91 | E4: =E5+E6-E7 -> 725671.32 | F4: =F5+F6-F7 -> 887809.23 | G4: =G5+G6-G7 -> 1119364.1 | H4: =H5+H6-H7 -> 1455726.4 | I4: =I5+I6-I7 -> 485004.77
C5: Premi Penutupan Langsung | D5: 715922.26 | E5: 828704.33 | F5: 984044.63 | G5: 1250023.7 | H5: 1546637 | I5: 553382.08
C6: Premi Penutupan Tidak Langsung | D6: 221.9259 | E6: 96.865067 | F6: 49.928393
C7: Komisi Dibayar | D7: 84923.277 | E7: 103129.87 | F7: 96285.332 | G7: 130659.55 | H7: 90910.619 | I7: 68377.31
B9: Beban Usaha | D9: =SUM(D10:D13) -> 139626.28 | E9: =SUM(E10:E13) -> 175311.84 | F9: =SUM(F10:F13) -> 165003.18 | G9: =SUM(G10:G13) -> 159706.74 | H9: =SUM(H10:H13) -> 174065.33 | I9: =SUM(I10:I13) -> 126131.93
C10: Beban Pemasaran | D10: 34944.518 | E10: 66394.975 | F10: 65821.887 | G10: 71064.306 | H10: 84491.544 | I10: 68441.214
C11: Beban Pegawai dan Pengurus | D11: 60947.395 | E11: 66717.217 | F11: 69290.973 | G11: 62839.272 | H11: 49923.441 | I11: 39861.899
C12: Beban Pendidikan dan Pelatihan | D12: 5387.7795 | E12: 6906.4187 | F12: 4800.4858 | G12: 4300.5856 | H12: 1805.3835 | I12: 1397.8239
C13: Beban Umum dan Administrasi Lainnya | D13: 38346.589 | E13: 35293.226 | F13: 25089.834 | G13: 21502.58 | H13: 37844.962 | I13: 16430.998
B15: Rasio Biaya | D15: =D9/D4 -> 0.22120034 | E15: =E9/E4 -> 0.24158573 | F15: =F9/F4 -> 0.18585432 | G15: =G9/G4 -> 0.14267631 | H15: =H9/H4 -> 0.11957283 | I15: =I9/I4 -> 0.26006328
C16: Beban Pemasaran | D16: =D10/D$4 -> 0.055360204 | E16: =E10/E$4 -> 0.091494556 | F16: =F10/F$4 -> 0.074139674 | G16: =G10/G$4 -> 0.063486319 | H16: =H10/H$4 -> 0.058040812 | I16: =I10/I$4 -> 0.14111452
C17: Beban Pegawai dan Pengurus | D17: =D11/D$4 -> 0.096554778 | E17: =E11/E$4 -> 0.091938615 | F17: =F11/F$4 -> 0.078047142 | G17: =G11/G$4 -> 0.056138367 | H17: =H11/H$4 -> 0.034294522 | I17: =I11/I$4 -> 0.082188673
C18: Beban Pendidikan dan Pelatihan | D18: =D12/D$4 -> 0.0085354896 | E18: =E12/E$4 -> 0.009517282 | F18: =F12/F$4 -> 0.0054071141 | G18: =G12/G$4 -> 0.0038419899 | H18: =H12/H$4 -> 0.0012401942 | I18: =I12/I$4 -> 0.0028820827
C19: Beban Umum dan Administrasi Lainnya | D19: =D13/D$4 -> 0.060749871 | E19: =E13/E$4 -> 0.048635277 | F19: =F13/F$4 -> 0.028260388 | G19: =G13/G$4 -> 0.019209639 | H19: =H13/H$4 -> 0.025997304 | I19: =I13/I$4 -> 0.033878012

Sheet SUMMARY
B3: 2020 | H3: 2023
B4: COB | C4: LOSS RASIO | D4: PAD | E4: EXPENSE | F4: TOTAL | H4: COB | I4: LOSS RASIO | J4: PAD | K4: EXPENSE | L4: TOTAL
B5: Property | C5: ='Loss Rasio Per COB'!C4 -> 0.51 | D5: =PAD!C4*C5 -> 0.03825 | E5: ='Expense Rasio'!D$15 -> 0.22120034 | F5: =SUM(C5:E5) -> 0.76945034 | H5: Property | I5: ='Loss Rasio Per COB'!F4 -> 0.76229247 | J5: =PAD!F4*SUMMARY!I5 -> 0.057171935 | K5: ='Expense Rasio'!G$15 -> 0.14267631 | L5: =SUM(I5:K5) -> 0.96214072
B6: Marine Cargo | C6: ='Loss Rasio Per COB'!C5 -> 0.12 | D6: =PAD!C5*C6 -> 0.009 | E6: ='Expense Rasio'!D$15 -> 0.22120034 | F6: =SUM(C6:E6) -> 0.35020034 | H6: Marine Cargo | I6: ='Loss Rasio Per COB'!F5 -> 0.22852501 | J6: =PAD!F5*SUMMARY!I6 -> 0.017139376 | K6: ='Expense Rasio'!G$15 -> 0.14267631 | L6: =SUM(I6:K6) -> 0.3883407
B7: Marine Hull | C7: ='Loss Rasio Per COB'!C6 -> 0.31 | D7: =PAD!C6*C7 -> 0.02325 | E7: ='Expense Rasio'!D$15 -> 0.22120034 | F7: =SUM(C7:E7) -> 0.55445034 | H7: Marine Hull | I7: ='Loss Rasio Per COB'!F6 -> 0.050898567 | J7: =PAD!F6*SUMMARY!I7 -> 0.0038173925 | K7: ='Expense Rasio'!G$15 -> 0.14267631 | L7: =SUM(I7:K7) -> 0.19739227
B8: Motor Vehicle | C8: ='Loss Rasio Per COB'!C7 -> 0.5 | D8: =PAD!C7*C8 -> 0.0375 | E8: ='Expense Rasio'!D$15 -> 0.22120034 | F8: =SUM(C8:E8) -> 0.75870034 | H8: Motor Vehicle | I8: ='Loss Rasio Per COB'!F7 -> 0.52412827 | J8: =PAD!F7*SUMMARY!I8 -> 0.03930962 | K8: ='Expense Rasio'!G$15 -> 0.14267631 | L8: =SUM(I8:K8) -> 0.7061142
B9: General Accident | C9: ='Loss Rasio Per COB'!C8 -> 0.68 | D9: =PAD!C8*C9 -> 0.051 | E9: ='Expense Rasio'!D$15 -> 0.22120034 | F9: =SUM(C9:E9) -> 0.95220034 | H9: General Accident | I9: ='Loss Rasio Per COB'!F8 -> 0.078311103 | J9: =PAD!F8*SUMMARY!I9 -> 0.0058733327 | K9: ='Expense Rasio'!G$15 -> 0.14267631 | L9: =SUM(I9:K9) -> 0.22686075
B10: General Engineering | C10: ='Loss Rasio Per COB'!C9 -> 0.75 | D10: =PAD!C9*C10 -> 0.05625 | E10: ='Expense Rasio'!D$15 -> 0.22120034 | F10: =SUM(C10:E10) -> 1.0274503 | H10: General Engineering | I10: ='Loss Rasio Per COB'!F9 -> 0.5291544 | J10: =PAD!F9*SUMMARY!I10 -> 0.03968658 | K10: ='Expense Rasio'!G$15 -> 0.14267631 | L10: =SUM(I10:K10) -> 0.71151729
B11: Liability | C11: ='Loss Rasio Per COB'!C10 -> 0.68 | D11: =PAD!C10*C11 -> 0.051 | E11: ='Expense Rasio'!D$15 -> 0.22120034 | F11: =SUM(C11:E11) -> 0.95220034 | H11: Liability | I11: ='Loss Rasio Per COB'!F10 -> 0.089811745 | J11: =PAD!F10*SUMMARY!I11 -> 0.0067358809 | K11: ='Expense Rasio'!G$15 -> 0.14267631 | L11: =SUM(I11:K11) -> 0.23922394
B12: Credit Stoploss | F12: =SUM(C12:E12) -> 0 | H12: Credit Stoploss | I12: ='Loss Rasio Per COB'!F11 -> 0.90140809 | L12: =SUM(I12:K12) -> 0.90140809
B13: Health | C13: ='Loss Rasio Per COB'!C12 -> 0.95 | D13: =PAD!C12*C13 -> 0.07125 | E13: ='Expense Rasio'!D$15 -> 0.22120034 | F13: =SUM(C13:E13) -> 1.2424503 | H13: Health | I13: ='Loss Rasio Per COB'!F12 -> 1.0364014 | J13: =PAD!F12*SUMMARY!I13 -> 0.077730102 | K13: ='Expense Rasio'!G$15 -> 0.14267631 | L13: =SUM(I13:K13) -> 1.2568078
B15: 2021 | H15: 2024
B16: COB | C16: LOSS RASIO | D16: PAD | E16: EXPENSE | F16: TOTAL | H16: COB | I16: LOSS RASIO | J16: PAD | K16: EXPENSE | L16: TOTAL
B17: Property | C17: ='Loss Rasio Per COB'!D4 -> 0.48 | D17: =PAD!D4*C17 -> 0.036 | E17: ='Expense Rasio'!E$15 -> 0.24158573 | F17: =SUM(C17:E17) -> 0.75758573 | H17: Property | I17: 1.226334 | J17: =PAD!G4*I17 -> 0.091975053 | K17: ='Expense Rasio'!H$15 -> 0.11957283 | L17: =SUM(I17:K17) -> 1.4378819
B18: Marine Cargo | C18: ='Loss Rasio Per COB'!D5 -> 0.07 | D18: =PAD!D5*C18 -> 0.00525 | E18: ='Expense Rasio'!E$15 -> 0.24158573 | F18: =SUM(C18:E18) -> 0.31683573 | H18: Marine Cargo | I18: 0.2508365 | J18: =PAD!G5*I18 -> 0.018812738 | K18: ='Expense Rasio'!H$15 -> 0.11957283 | L18: =SUM(I18:K18) -> 0.38922207
B19: Marine Hull | C19: ='Loss Rasio Per COB'!D6 -> 0.29 | D19: =PAD!D6*C19 -> 0.02175 | E19: ='Expense Rasio'!E$15 -> 0.24158573 | F19: =SUM(C19:E19) -> 0.55333573 | H19: Marine Hull | I19: 0.11952308 | J19: =PAD!G6*I19 -> 0.0089642311 | K19: ='Expense Rasio'!H$15 -> 0.11957283 | L19: =SUM(I19:K19) -> 0.24806014
B20: Motor Vehicle | C20: ='Loss Rasio Per COB'!D7 -> 0.45 | D20: =PAD!D7*C20 -> 0.03375 | E20: ='Expense Rasio'!E$15 -> 0.24158573 | F20: =SUM(C20:E20) -> 0.72533573 | H20: Motor Vehicle | I20: 0.59947946 | J20: =PAD!G7*I20 -> 0.04496096 | K20: ='Expense Rasio'!H$15 -> 0.11957283 | L20: =SUM(I20:K20) -> 0.76401325
B21: General Accident | C21: ='Loss Rasio Per COB'!D8 -> 0.67 | D21: =PAD!D8*C21 -> 0.05025 | E21: ='Expense Rasio'!E$15 -> 0.24158573 | F21: =SUM(C21:E21) -> 0.96183573 | H21: General Accident | I21: 0.075049447 | J21: =PAD!G8*I21 -> 0.0056287085 | K21: ='Expense Rasio'!H$15 -> 0.11957283 | L21: =SUM(I21:K21) -> 0.20025099
B22: General Engineering | C22: ='Loss Rasio Per COB'!D9 -> 0.56 | D22: =PAD!D9*C22 -> 0.042 | E22: ='Expense Rasio'!E$15 -> 0.24158573 | F22: =SUM(C22:E22) -> 0.84358573 | H22: General Engineering | I22: 0.26225301 | J22: =PAD!G9*I22 -> 0.019668976 | K22: ='Expense Rasio'!H$15 -> 0.11957283 | L22: =SUM(I22:K22) -> 0.40149482
B23: Liability | C23: ='Loss Rasio Per COB'!D10 -> 0.67 | D23: =PAD!D10*C23 -> 0.05025 | E23: ='Expense Rasio'!E$15 -> 0.24158573 | F23: =SUM(C23:E23) -> 0.96183573 | H23: Liability | I23: 1.0417618 | J23: =PAD!G10*I23 -> 0.078132138 | K23: ='Expense Rasio'!H$15 -> 0.11957283 | L23: =SUM(I23:K23) -> 1.2394668
B24: Credit Stoploss | F24: =SUM(C24:E24) -> 0 | H24: Credit Stoploss | I24: 0.88546239 | L24: =SUM(I24:K24) -> 0.88546239
B25: Health | C25: ='Loss Rasio Per COB'!D12 -> 0.84 | D25: =PAD!D12*C25 -> 0.063 | E25: ='Expense Rasio'!E$15 -> 0.24158573 | F25: =SUM(C25:E25) -> 1.1445857 | H25: Health | I25: 0.62716313 | J25: =PAD!G12*I25 -> 0.047037235 | K25: ='Expense Rasio'!H$15 -> 0.11957283 | L25: =SUM(I25:K25) -> 0.79377319
B27: 2022 | H27: 2025
B28: COB | C28: LOSS RASIO | D28: PAD | E28: EXPENSE | F28: TOTAL | H28: COB | I28: LOSS RASIO | J28: PAD | K28: EXPENSE | L28: TOTAL
B29: Property | C29: ='Loss Rasio Per COB'!E4 -> 0.431 | D29: =PAD!E4*C29 -> 0.032325 | E29: ='Expense Rasio'!F$15 -> 0.18585432 | F29: =SUM(C29:E29) -> 0.64917932 | H29: Property | I29: 0.25460701 | J29: =PAD!H4*I29 -> 0.046676514 | K29: ='Expense Rasio'!I$15 -> 0.26006328 | L29: =SUM(I29:K29) -> 0.56134681
B30: Marine Cargo | C30: ='Loss Rasio Per COB'!E5 -> 0.046 | D30: =PAD!E5*C30 -> 0.00345 | E30: ='Expense Rasio'!F$15 -> 0.18585432 | F30: =SUM(C30:E30) -> 0.23530432 | H30: Marine Cargo | I30: 0.1525408 | J30: =PAD!H5*I30 -> 0.028243241 | K30: ='Expense Rasio'!I$15 -> 0.26006328 | L30: =SUM(I30:K30) -> 0.44084733
B31: Marine Hull | C31: ='Loss Rasio Per COB'!E6 -> 0.046 | D31: =PAD!E6*C31 -> 0.00345 | E31: ='Expense Rasio'!F$15 -> 0.18585432 | F31: =SUM(C31:E31) -> 0.23530432 | H31: Marine Hull | I31: 0.017122117 | J31: =PAD!H6*I31 -> 0.0022759477 | K31: ='Expense Rasio'!I$15 -> 0.26006328 | L31: =SUM(I31:K31) -> 0.27946135
B32: Motor Vehicle | C32: ='Loss Rasio Per COB'!E7 -> 0.431 | D32: =PAD!E7*C32 -> 0.032325 | E32: ='Expense Rasio'!F$15 -> 0.18585432 | F32: =SUM(C32:E32) -> 0.64917932 | H32: Motor Vehicle | I32: 0.50675333 | J32: =PAD!H7*I32 -> 0.035567121 | K32: ='Expense Rasio'!I$15 -> 0.26006328 | L32: =SUM(I32:K32) -> 0.80238373
B33: General Accident | C33: ='Loss Rasio Per COB'!E8 -> 0.741 | D33: =PAD!E8*C33 -> 0.055575 | E33: ='Expense Rasio'!F$15 -> 0.18585432 | F33: =SUM(C33:E33) -> 0.98242932 | H33: General Accident | I33: 0.054712509 | J33: =PAD!H8*I33 -> 0.0072726292 | K33: ='Expense Rasio'!I$15 -> 0.26006328 | L33: =SUM(I33:K33) -> 0.32204842
B34: General Engineering | C34: ='Loss Rasio Per COB'!E9 -> 0.234 | D34: =PAD!E9*C34 -> 0.01755 | E34: ='Expense Rasio'!F$15 -> 0.18585432 | F34: =SUM(C34:E34) -> 0.43740432 | H34: General Engineering | I34: 0.21827839 | J34: =PAD!H9*I34 -> 0.029014531 | K34: ='Expense Rasio'!I$15 -> 0.26006328 | L34: =SUM(I34:K34) -> 0.50735621
B35: Liability | C35: ='Loss Rasio Per COB'!E10 -> 0.741 | D35: =PAD!E10*C35 -> 0.055575 | E35: ='Expense Rasio'!F$15 -> 0.18585432 | F35: =SUM(C35:E35) -> 0.98242932 | H35: Liability | I35: 0.0318734 | J35: =PAD!H10*I35 -> 0.0042367536 | K35: ='Expense Rasio'!I$15 -> 0.26006328 | L35: =SUM(I35:K35) -> 0.29617344
B36: Credit Stoploss | F36: =SUM(C36:E36) -> 0 | H36: Credit Stoploss | I36: 0.56927249 | L36: =SUM(I36:K36) -> 0.56927249
B37: Health | C37: ='Loss Rasio Per COB'!E12 -> 0.668 | D37: =PAD!E12*C37 -> 0.0501 | E37: ='Expense Rasio'!F$15 -> 0.18585432 | F37: =SUM(C37:E37) -> 0.90395432 | H37: Health | I37: 0.40093522 | J37: =PAD!H12*I37 -> 0.061921247 | K37: ='Expense Rasio'!I$15 -> 0.26006328 | L37: =SUM(I37:K37) -> 0.72291975
